dicomtrolley/__init__.py
dicomtrolley/auth.py
dicomtrolley/caching.py
dicomtrolley/core.py
dicomtrolley/datastructures.py
dicomtrolley/dicom_qr.py
dicomtrolley/exceptions.py
dicomtrolley/fields.py
dicomtrolley/http.py
dicomtrolley/logs.py
dicomtrolley/mint.py
dicomtrolley/parsing.py
dicomtrolley/qido_rs.py
dicomtrolley/rad69.py
dicomtrolley/servers.py
dicomtrolley/storage.py
dicomtrolley/trolley.py
dicomtrolley/wado_rs.py
dicomtrolley/wado_uri.py
dicomtrolley/xml_templates.py
dicomtrolley-4.1.0.dist-info/licenses/LICENSE
dicomtrolley-4.1.0.dist-info/METADATA
dicomtrolley-4.1.0.dist-info/WHEEL
dicomtrolley-4.1.0.dist-info/top_level.txt
dicomtrolley-4.1.0.dist-info/RECORD
