Metadata-Version: 2.4
Name: dicomtrolley
Version: 4.1.0
Summary: Retrieve medical images via WADO-URI, WADO-RS, QIDO-RS, MINT, RAD69 and DICOM-QR
Author-email: Sjoerd Kerkstra <sjoerd.kerkstra@radboudumc.nl>
License-Expression: Apache-2.0
Project-URL: Repository, https://github.com/sjoerdk/dicomtrolley
Project-URL: Changelog, https://github.com/sjoerdk/dicomtrolley/blob/main/HISTORY.md
Keywords: DICOM,DICOM-web,QIDO,WADO,MINT,RAD69,Download
Classifier: Programming Language :: Python :: 3.10
Classifier: Programming Language :: Python :: 3.11
Classifier: Programming Language :: Python :: 3.12
Requires-Python: >=3.10
License-File: LICENSE
Requires-Dist: requests
Requires-Dist: pydicom>=3.0.1
Requires-Dist: requests-futures>=1.0.0
Requires-Dist: pynetdicom
Requires-Dist: Jinja2
Requires-Dist: requests-toolbelt>=1.0.0
Requires-Dist: pydantic>=2
Dynamic: license-file
